keg_bouncer/__init__.py
keg_bouncer/auth.py
keg_bouncer/tokens.py
keg_bouncer/version.py
keg_bouncer/alembic/README
keg_bouncer/alembic/env.py
keg_bouncer/alembic/script.py.mako
keg_bouncer/alembic/versions/588daaa98ab1_initial_revision.py
keg_bouncer/model/__init__.py
keg_bouncer/model/entities.py
keg_bouncer/model/interfaces.py
keg_bouncer/model/mixins.py
keg_bouncer/model/utils.py
KegBouncer-2.2.4.dist-info/LICENSE
KegBouncer-2.2.4.dist-info/METADATA
KegBouncer-2.2.4.dist-info/WHEEL
KegBouncer-2.2.4.dist-info/top_level.txt
KegBouncer-2.2.4.dist-info/RECORD
