Metadata-Version: 2.1
Name: KegBouncer
Version: 2.2.4
Summary: A three-tiered permissions model for KegElements built atop Flask-User
Home-page: https://github.com/level12/keg-bouncer
Author: Level 12
Author-email: devteam@level12.io
License: UNKNOWN
Platform: UNKNOWN
Classifier: Development Status :: 4 - Beta
Classifier: Intended Audience :: Developers
Classifier: License :: OSI Approved :: BSD License
Classifier: Operating System :: OS Independent
Classifier: Programming Language :: Python :: 2.7
Classifier: Programming Language :: Python :: 3.5
Requires-Dist: Flask-Login
Requires-Dist: Keg
Requires-Dist: KegElements
Requires-Dist: cryptography
Requires-Dist: six
Requires-Dist: SQLAlchemy
Requires-Dist: wrapt
